music_dl/MusicDL.py
music_dl/__init__.py
music_dl/core/__init__.py
music_dl/core/args.py
music_dl/core/error.py
music_dl/core/metadata.py
music_dl/core/playlist.py
music_dl/core/youtube_dl.py
music_dl/lib/__init__.py
music_dl/lib/dir.py
music_dl/lib/log.py
music_dl/lib/util.py
music_dl/util/__init__.py
music_dl-0.2.1.dist-info/LICENSE.txt
music_dl-0.2.1.dist-info/METADATA
music_dl-0.2.1.dist-info/WHEEL
music_dl-0.2.1.dist-info/entry_points.txt
music_dl-0.2.1.dist-info/top_level.txt
music_dl-0.2.1.dist-info/RECORD
