Metadata-Version: 2.1
Name: music-dl
Version: 0.2.1
Summary: Command line tool to download music from YouTube and SoundCloud
Home-page: http://github.com/gumob/music-dl
Author: Gumob
Author-email: hello@gumob.com
License: MIT
Project-URL: Bug Reports, https://github.com/gumob/music-dl/issues
Project-URL: Funding, https://donate.pypi.org
Project-URL: Source, https://github.com/gumob/music-dl/
Keywords: youtube,soundcloud,download,mp3,m4a,flac,youtube-dl,youtubedl
Platform: posix
Classifier: Development Status :: 3 - Alpha
Classifier: License :: OSI Approved :: MIT License
Classifier: Programming Language :: Python :: 3.4
Classifier: Programming Language :: Python :: 3.5
Classifier: Programming Language :: Python :: 3.6
Requires-Python: >=3.4
Requires-Dist: clipboard
Requires-Dist: colorama
Requires-Dist: mutagen
Requires-Dist: pathlib
Requires-Dist: python-magic
Requires-Dist: tldextract
Requires-Dist: youtube-dl
